{
    "Recipe Title": "Baqarkhani Roti Recipe",
    "Recipe Info": {
        "Total Cook Time": "1 hr 25 mins",
        "Prep Time": "25 mins",
        "Cook Time": "1 hr",
        "Recipe Servings": "6",
        "Expert": "N/A"
    },
    "Ingredients": [
        "Oven Temp: 375 F-190 C",
        "4 Cups Refined flour",
        "1 1/2 tsp Baking powder",
        "1 Cup Ghee",
        "1 tsp Salt",
        "1 Tbsp Sugar",
        "1 Cup Milk",
        "2 Tbsp Raisins",
        "1 Cup Almonds, sliced",
        "1 tsp Screw pine (kewra) essence",
        "To sprinkle  Poppy seeds (khus khus)"
    ],
    "Main Title": "How to Make Baqarkhani Roti",
    "Steps": {}
}